ttpdant/Cnn.py
ttpdant/Rnn-lstm.py
ttpdant/__init__.py
ttpdant/adam.py
ttpdant/autoencoder.py
ttpdant/fnn-perceptron.py
ttpdant/mc-culloch-pitt.py
ttpdant/mini-batch-gd.py
ttpdant/momentum-gd.py
ttpdant/nestrov-gd.py
ttpdant/optimization-adagrad-gd.py
ttpdant/optimization-stocastic-gd.py
ttpdant/optimization-vanilla-gd.py
ttpdant/rms.py
ttpdant-1.0.dist-info/METADATA
ttpdant-1.0.dist-info/WHEEL
ttpdant-1.0.dist-info/top_level.txt
ttpdant-1.0.dist-info/RECORD
