Metadata-Version: 2.1
Name: ttpdant
Version: 1.0
Summary: The Tortured Poets Department
Home-page: https://taylorswift.com
Author: Taylor Swift
Author-email: taylor@swift.com
License: UNKNOWN
Platform: UNKNOWN
